cohere_core/controller/AI_guess.py
cohere_core/controller/__init__.py
cohere_core/controller/features.py
cohere_core/controller/op_flow.py
cohere_core/controller/phasing.py
cohere_core/data/__init__.py
cohere_core/data/alien_tools.py
cohere_core/data/standard_preprocess.py
cohere_core/lib/__init__.py
cohere_core/lib/check_libs.py
cohere_core/lib/cohlib.py
cohere_core/lib/cplib.py
cohere_core/lib/nplib.py
cohere_core/lib/torchlib.py
cohere_core/utilities/__init__.py
cohere_core/utilities/config_errors_dict.py
cohere_core/utilities/config_verifier.py
cohere_core/utilities/dvc_utils.py
cohere_core/utilities/ga_utils.py
cohere_core/utilities/utils.py
cohere_core-4.4.0.dist-info/licenses/LICENSE
cohere_core-4.4.0.dist-info/METADATA
cohere_core-4.4.0.dist-info/WHEEL
cohere_core-4.4.0.dist-info/top_level.txt
cohere_core-4.4.0.dist-info/RECORD
