Metadata-Version: 2.4
Name: cohere_core
Version: 4.4.0
Summary: cohere reconstruction tools
Author-email: Barbara Frosik <bfrosik@anl.gov>, Ross Harder <rharder@anl.gov>
License: Copyright © 2019, UChicago Argonne, LLC
Project-URL: Homepage, https://github.com/AdvancedPhotonSource/cohere
Project-URL: Documentation, https://readthedocs.org
Project-URL: Repository, https://github.com//AdvancedPhotonSource/cohere.git
Classifier: Programming Language :: Python :: 3
Classifier: Operating System :: OS Independent
Requires-Python: >=3.11
License-File: LICENSE
Requires-Dist: numpy<2
Requires-Dist: scikit-learn
Requires-Dist: tifffile
Requires-Dist: psutil
Requires-Dist: tqdm
Requires-Dist: matplotlib
Requires-Dist: scipy==1.14.1
Requires-Dist: sphinx
Requires-Dist: sphinx-pyproject
Dynamic: license-file
